{
  "name": "gperftools",
  "versions": [
    "master",
    "master-issue_626",
    "google-perftools-1.8.1",
    "google-perftools-1.8.2",
    "google-perftools-1.8.3",
    "google-perftools-1.9.1",
    "gperftools-2.1.90",
    "gperftools-2.1.90^{}",
    "gperftools-2.10.80",
    "gperftools-2.10.80^{}",
    "gperftools-2.2.1",
    "gperftools-2.2.1^{}",
    "gperftools-2.2.90",
    "gperftools-2.2.90^{}",
    "gperftools-2.3.90",
    "gperftools-2.3.90^{}",
    "gperftools-2.4.90",
    "gperftools-2.4.90^{}",
    "gperftools-2.4.91",
    "gperftools-2.4.91^{}",
    "gperftools-2.5.90",
    "gperftools-2.5.90^{}",
    "gperftools-2.5.91",
    "gperftools-2.5.91^{}",
    "gperftools-2.5.92",
    "gperftools-2.5.92^{}",
    "gperftools-2.5.93",
    "gperftools-2.5.93^{}",
    "gperftools-2.6.1",
    "gperftools-2.6.1^{}",
    "gperftools-2.6.2",
    "gperftools-2.6.2^{}",
    "gperftools-2.6.3",
    "gperftools-2.6.3^{}",
    "gperftools-2.6.90",
    "gperftools-2.6.90^{}",
    "gperftools-2.7.90",
    "gperftools-2.7.90^{}",
    "gperftools-2.8.1",
    "gperftools-2.8.1^{}",
    "gperftools-2.8.90",
    "gperftools-2.8.90^{}",
    "gperftools-2.9.1",
    "gperftools-2.9.1^{}",
    "perftools-0.94.1",
    "perftools-0.95.1",
    "perftools-0.99.1",
    "perftools-0.99.2"
  ],
  "git": "https://github.com/gperftools/gperftools",
  "git_short": "gperftools/gperftools",
  "git_prefixed": "gh:gperftools/gperftools",
  "stars": 7866,
  "forks": 1468,
  "open_issues": 116,
  "maintainers": [],
  "watchers": 367,
  "description": "High-performance multi-threaded malloc()",
  "git_description": "",
  "target_link": "",
  "license": "BSD 3-Clause \"New\" or \"Revised\" License",
  "language": "C++",
  "owner": "gperftools",
  "owner_type": "Organization"
}